sequence_detector/alu.sv
module alu (
    input clk,
    input reset,       
    input data,
    output start_shifting,
    output [3:0] state_out // Expose state for debugging
);
    
    reg [3:0] state;
    
    assign start_shifting = (state == 4'd4);
    assign state_out = state; // Assign internal state to output signal
    
    always @(posedge clk) begin
        if (reset) begin
            state <= 4'b0000;
        end else begin
            case (state)
                4'd0: state <= data ? 4'd1 : 4'd0;
                4'd1: state <= data ? 4'd2 : 4'd0;
                4'd2: state <= data ? 4'd0 : 4'd3;
                4'd3: state <= data ? 4'd4 : 4'd0;
                4'd4: state <= 4'd0; // Stay in state 4
                default: state <= 4'd0;
            endcase
        end
    end

endmodule

sequence_detector/trace.vcd
$version Generated by VerilatedVcd $end
$date Thu May 30 01:01:03 2024
 $end
$timescale   1ps $end

 $scope module TOP $end
  $var wire  1 # clk $end
  $var wire  1 % data $end
  $var wire  1 $ reset $end
  $var wire  1 & start_shifting $end
  $var wire  4 ' state_out [3:0] $end
  $scope module alu $end
   $var wire  1 # clk $end
   $var wire  1 % data $end
   $var wire  1 $ reset $end
   $var wire  1 & start_shifting $end
   $var wire  4 ( state [3:0] $end
   $var wire  4 ' state_out [3:0] $end
  $upscope $end
 $upscope $end
$enddefinitions $end


#0
1#
1$
0%
0&
b0000 '
b0000 (
#1
0#
#2
1#
#3
0#
#4
1#
#5
0#
#6
1#
0$
#7
0#
#8
1#
#9
0#
#10
1#
#11
0#
1%
#12
1#
0%
#13
0#
1%
#14
1#
0%
#15
0#
#16
1#
#17
0#
1%
#18
1#
0%
