sequence_detector/alu.sv
module alu (
    input clk,
    input reset,       
    input data,
    output start_shifting,
    output [3:0] state_out // Expose state for debugging
);
    
    reg [3:0] state;
    
    assign start_shifting = (state == 4'd4);
    assign state_out = state; // Assign internal state to output signal
    
    always @(posedge clk) begin
        if (reset) begin
            state <= 4'b0000;
        end else begin
            case (state)
                4'd0: state <= data ? 4'd1 : 4'd0;
                4'd1: state <= data ? 4'd2 : 4'd0;
                4'd2: state <= data ? 4'd0 : 4'd3;
                4'd3: state <= data ? 4'd4 : 4'd0;
                4'd4: state <= 4'd0; // Stay in state 4
                default: state <= 4'd0;
            endcase
        end
    end

endmodule

sequence_detector/waveform.vcd
$version Generated by VerilatedVcd $end
$date Thu May 30 18:31:00 2024
 $end
$timescale   1ps $end

 $scope module TOP $end
  $var wire  1 # clk $end
  $var wire  1 % data $end
  $var wire  1 $ reset $end
  $var wire  1 & start_shifting $end
  $var wire  4 ' state_out [3:0] $end
  $scope module alu $end
   $var wire  1 # clk $end
   $var wire  1 % data $end
   $var wire  1 $ reset $end
   $var wire  1 & start_shifting $end
   $var wire  4 ( state [3:0] $end
   $var wire  4 ' state_out [3:0] $end
  $upscope $end
 $upscope $end
$enddefinitions $end


#0
1#
1$
0%
0&
b0000 '
b0000 (
#1
0#
#2
1#
#3
0#
#4
1#
#5
0#
#6
1#
#7
0#
#8
1#
#9
0#
#10
1#
0$
1%
b0001 '
b0001 (
#11
0#
#12
1#
b0010 '
b0010 (
#13
0#
#14
1#
0%
b0011 '
b0011 (
#15
0#
#16
1#
1%
1&
b0100 '
b0100 (
#17
0#
#18
1#
0&
b0000 '
b0000 (
#19
0#
#20
1#
b0001 '
b0001 (
#21
0#
#22
1#
0%
b0000 '
b0000 (
#23
0#
#24
1#
1%
b0001 '
b0001 (
#25
0#
#26
1#
b0010 '
b0010 (
#27
0#
#28
1#
b0000 '
b0000 (
#29
0#
#30
1#
0%
#31
0#
#32
1#
1%
b0001 '
b0001 (
#33
0#
#34
1#
b0010 '
b0010 (
#35
0#
#36
1#
b0000 '
b0000 (
#37
0#
#38
1#
0%
#39
0#
#40
1#
1%
b0001 '
b0001 (
#41
0#
#42
1#
b0010 '
b0010 (
#43
0#
#44
1#
b0000 '
b0000 (
#45
0#
#46
1#
0%
#47
0#
#48
1#
1%
b0001 '
b0001 (
#49
0#
#50
1#
b0010 '
b0010 (
#51
0#
#52
1#
b0000 '
b0000 (
#53
0#
#54
1#
0%
#55
0#
#56
1#
1%
b0001 '
b0001 (
#57
0#
#58
1#
b0010 '
b0010 (
#59
0#
#60
1#
b0000 '
b0000 (
#61
0#
#62
1#
0%
#63
0#
#64
1#
1%
b0001 '
b0001 (
#65
0#
#66
1#
b0010 '
b0010 (
#67
0#
#68
1#
b0000 '
b0000 (
#69
0#
#70
1#
0%
#71
0#
#72
1#
1%
b0001 '
b0001 (
#73
0#
#74
1#
b0010 '
b0010 (
#75
0#
#76
1#
b0000 '
b0000 (
#77
0#
#78
1#
0%
#79
0#
#80
1#
1%
b0001 '
b0001 (
#81
0#
#82
1#
b0010 '
b0010 (
#83
0#
#84
1#
b0000 '
b0000 (
#85
0#
#86
1#
0%
#87
0#
#88
1#
1%
b0001 '
b0001 (
#89
0#
#90
1#
b0010 '
b0010 (
#91
0#
#92
1#
b0000 '
b0000 (
#93
0#
#94
1#
0%
#95
0#
#96
1#
1%
b0001 '
b0001 (
#97
0#
#98
1#
b0010 '
b0010 (
#99
0#
#100
1#
b0000 '
b0000 (
#101
0#
#102
1#
0%
#103
0#
#104
1#
1%
b0001 '
b0001 (
#105
0#
#106
1#
b0010 '
b0010 (
#107
0#
#108
1#
b0000 '
b0000 (
#109
0#
#110
1#
0%
#111
0#
#112
1#
1%
b0001 '
b0001 (
#113
0#
#114
1#
b0010 '
b0010 (
#115
0#
#116
1#
b0000 '
b0000 (
#117
0#
#118
1#
0%
#119
0#
#120
1#
1%
b0001 '
b0001 (
#121
0#
#122
1#
b0010 '
b0010 (
#123
0#
#124
1#
b0000 '
b0000 (
#125
0#
#126
1#
0%
#127
0#
#128
1#
1%
b0001 '
b0001 (
#129
0#
#130
1#
b0010 '
b0010 (
#131
0#
#132
1#
b0000 '
b0000 (
#133
0#
#134
1#
0%
#135
0#
#136
1#
1%
b0001 '
b0001 (
#137
0#
#138
1#
b0010 '
b0010 (
#139
0#
#140
1#
b0000 '
b0000 (
#141
0#
#142
1#
0%
#143
0#
#144
1#
1%
b0001 '
b0001 (
#145
0#
#146
1#
b0010 '
b0010 (
#147
0#
#148
1#
b0000 '
b0000 (
